samlauthenticator/__init__.py
samlauthenticator/samlauthenticator.py
jupyterhub_samlauthenticator-0.0.11.dist-info/LICENSE.txt
jupyterhub_samlauthenticator-0.0.11.dist-info/METADATA
jupyterhub_samlauthenticator-0.0.11.dist-info/WHEEL
jupyterhub_samlauthenticator-0.0.11.dist-info/top_level.txt
jupyterhub_samlauthenticator-0.0.11.dist-info/RECORD
