Metadata-Version: 2.2
Name: jupyterhub-samlauthenticator
Version: 0.0.11
Summary: SAML Authenticator for JupyterHub
Home-page: https://github.com/bluedatainc/jupyterhub-samlauthenticator
Author: Tom Kelley
Author-email: Tom Kelley <distortedsignal@gmail.com>
License: MIT
Project-URL: Homepage, https://github.com/HewlettPackard/jupyterhub-samlauthenticator
Project-URL: Issues, https://github.com/HewlettPackard/jupyterhub-samlauthenticator/issues
Classifier: Programming Language :: Python :: 3
Classifier: Programming Language :: Python :: 3.7
Classifier: Programming Language :: Python :: 3.8
Classifier: Programming Language :: Python :: 3.9
Classifier: Programming Language :: Python :: 3.10
Classifier: Programming Language :: Python :: 3.11
Classifier: Programming Language :: Python :: 3.12
Classifier: Programming Language :: Python :: 3.13
Classifier: License :: OSI Approved :: MIT License
Classifier: Operating System :: OS Independent
Requires-Python: >=3.6
License-File: LICENSE.txt
Requires-Dist: Jinja2>=2.4
Requires-Dist: jupyterhub>=0.9.0
Requires-Dist: lxml>=4.2.1
Requires-Dist: signxml>=2.6.0
Requires-Dist: pytz>=2019.1
Dynamic: author
Dynamic: home-page
